{
    "linear": "linear",
    "regression": "linear",
    "linearregression": "linear",
    "linearclassifier": "linear",
    "logistic": "linear",
    "logisticregression": "linear",

    "linear L2": "linear L2",
    "ridge": "linear L2",
    "ridgeclassifier": "linear L2",
    "ridgeCV": "linear L2",
    "ridgeclassifiercv": "linear L2",
    "l2": "linear L2",

    "lasso": "linear L1",
    "linear L1": "linear L1",

    "elasticnet": "elastic-net",
    "linear L1 L2": "elastic-net",
    "elastic-net": "elastic-net",
    "elastic net": "elastic-net",

    "tweedie": "Tweedie",
    "poisson": "Tweedie",
    "gaussian linear": "Tweedie",
    "tweedieregressor": "Tweedie",

    "ransac": "linear random sample consensus",
    "random sample consensus": "linear random sample consensus",
    "ransacregressor": "linear random sample consensus",
    "linear random sample consensus": "linear random sample consensus",

    "quantile": "linear quantile",
    "quantileregressor": "linear quantile",

    "passiveagressive": "linear passive aggressive",
    "passiveaggressiveregressor": "linear passive aggressive",
    "linear passive aggressive": "linear passive aggressive",
    "passive aggressive": "linear passive aggressive",

    "Bayesian": "Gaussian Bayes",
    "bayes": "Gaussian Bayes",
    "bayesian": "Gaussian Bayes",
    "naive": "Gaussian Bayes",
    "naive bayes": "Gaussian Bayes",
    "naivebayes": "Gaussian Bayes",
    "bayesianridge": "Gaussian Bayes",
    "gaussiannb": "Gaussian Bayes",

    "ardregression": "complement Bayes",
    "ardregressor": "complement Bayes",
    "complement Bayes": "complement Bayes",
    "complementnb": "complement Bayes",

    "multinomialnb": "multinomial Bayes",

    "bernoullinb": "Bernoulli Bayes",

    "theilsen": "linear Theil-Sen",
    "theil-sen": "linear Theil-Sen",
    "theil sen": "linear Theil-Sen",
    "linear theil-sen": "linear Theil-Sen",

    "lassolars": "least angle L1",
    "lassolarscv": "least angle L1",
    "least angle lasso": "least angle L1",
    "lasso least angle": "least angle L1",
    "lasso lars": "least angle L1",
    "lasso lars cv": "least angle L1",
    "lars lasso": "least angle L1",
    "lars lasso cv": "least angle L1",
    "least angle l1": "least angle L1",

    "linear least angle": "linear least angle",
    "lars": "linear least angle",
    "larsCV": "linear least angle",
    "least angle regression": "linear least angle",
    "least angle": "linear least angle",

    "decision tree": "decision tree",
    "tree": "decision tree",
    "decision": "decision tree",
    "decisiontree": "decision tree",
    "decisiontreeregressor": "decision tree",
    "decisiontreeclassifier": "decision tree",

    "linear tree": "linear tree",
    "linear decision tree": "linear tree",
    "decision linear": "linear tree",
    "lineartreeregressor": "linear tree",
    "lineartreeclassifier": "linear tree",

    "k-nearest neighbours": "k-nearest neighbours",
    "k-nearest": "k-nearest neighbours",
    "nearest neighbour": "k-nearest neighbours",
    "nearest neighbours": "k-nearest neighbours",
    "nearest neighbor": "k-nearest neighbours",
    "knn": "k-nearest neighbours",
    "nearest neighbors": "k-nearest neighbours",
    "k-neighbor": "k-nearest neighbours",
    "k-neighbour": "k-nearest neighbours",
    "kneighbor": "k-nearest neighbours",
    "kneighbour": "k-nearest neighbours",
    "neighbour": "k-nearest neighbours",
    "k neighbour": "k-nearest neighbours",
    "k neighbor": "k-nearest neighbours",
    "k neighbours": "k-nearest neighbours",
    "k neighbors": "k-nearest neighbours",
    "kneighborsregressor": "k-nearest neighbours",
    "neighbours": "k-nearest neighbours",
    "kneighborsclassifier": "k-nearest neighbours",

    "linearsvr": "linear support vector machine",
    "linearsvc": "linear support vector machine",
    "linearsvm": "linear support vector machine",
    "linear support vector machine": "linear support vector machine",

    "support vector machine": "radial support vector machine",
    "support vector": "radial support vector machine",
    "support vector regression": "radial support vector machine",
    "support vectors": "radial support vector machine",
    "svr": "radial support vector machine",
    "svc": "radial support vector machine",
    "svm": "radial support vector machine",
    "radialsvr": "radial support vector machine",
    "radialsvc": "radial support vector machine",
    "radialsvm": "radial support vector machine",
    "radial support vector machine": "radial support vector machine",

    "sigmoidsvr": "sigmoid support vector machine",
    "sigmoidsvc": "sigmoid support vector machine",
    "sigmoidsvm": "sigmoid support vector machine",
    "sigmoid support vector machine": "sigmoid support vector machine",

    "polysvr": "polynomial support vector machine",
    "polysvc": "polynomial support vector machine",
    "polysvm": "polynomial support vector machine",
    "polynomial support vector machine": "polynomial support vector machine",

    "linearrvr": "linear relevance vector machine",
    "linearrvc": "linear relevance vector machine",
    "linearrvm": "linear relevance vector machine",
    "linear relevance vector machine": "linear relevance vector machine",

    "relevance vector machine": "radial relevance vector machine",
    "relevance vector": "radial relevance vector machine",
    "rvr": "radial relevance vector machine",
    "relevance vector regression": "radial relevance vector machine",
    "relevance vectors": "radial relevance vector machine",
    "emrvr": "radial relevance vector machine",
    "rvc": "radial relevance vector machine",
    "emrvc": "radial relevance vector machine",
    "emrvm": "radial relevance vector machine",
    "rvm": "radial relevance vector machine",
    "radialrvr": "radial relevance vector machine",
    "radialrvc": "radial relevance vector machine",
    "radialrvm": "radial relevance vector machine",
    "radial relevance vector machine": "radial relevance vector machine",

    "sigmoidrvr": "sigmoid relevance vector machine",
    "sigmoidrvc": "sigmoid relevance vector machine",
    "sigmoidrvm": "sigmoid relevance vector machine",
    "sigmoid relevance vector machine": "sigmoid relevance vector machine",

    "polyrvr": "polynomial relevance vector machine",
    "polyrvc": "polynomial relevance vector machine",
    "polyrvm": "polynomial relevance vector machine",
    "polynomial relevance vector machine": "polynomial relevance vector machine",

    "Gaussian processes": "Gaussian processes",
    "gaussian": "Gaussian processes",
    "gaussian process": "Gaussian processes",
    "gaussian processes": "Gaussian processes",
    "gaussian process regressor": "Gaussian processes",
    "gaussianprocess": "Gaussian processes",
    "gaussianprocesses": "Gaussian processes",
    "gaussianprocessregressor": "Gaussian processes",
    "gaussianprocessclassifier": "Gaussian processes",

    "AdaBoost": "AdaBoost",
    "adaboost": "AdaBoost",
    "ada": "AdaBoost",
    "adaboosting": "AdaBoost",
    "adaboostregressor": "AdaBoost",
    "adaboostclassifier": "AdaBoost",

    "bagging": "bagging",
    "bags": "bagging",
    "bag": "bagging",
    "bagging boosting": "bagging",
    "baggingregressor": "bagging",
    "baggingclassifier": "bagging",

    "random forest": "random forest",
    "forest": "random forest",
    "random": "random forest",
    "randomforest": "random forest",
    "forest regressor": "random forest",
    "random forest regressor": "random forest",
    "randomforestregressor": "random forest",
    "randomforestclassifier": "random forest",

    "linear forest": "linear forest",
    "linear random forest": "linear forest",
    "linearforestregressor": "linear forest",
    "linearforestclassifier": "linear forest",

    "extra trees": "extra trees",
    "extra": "extra trees",
    "extratrees": "extra trees",
    "extratreesregressor": "extra trees",
    "extratreesclassifier": "extra trees",

    "gradient boosting": "gradient boosting",
    "boosting": "gradient boosting",
    "gradientboosting": "gradient boosting",
    "boosting regressor": "gradient boosting",
    "gradient boosting regressor": "gradient boosting",
    "gradientboostingregressor": "gradient boosting",
    "gradientboostingclassifier": "gradient boosting",
    "gradient boosting classifier": "gradient boosting",

    "linear boost": "linear gradient boosting",
    "linear boosting": "linear gradient boosting",
    "linear gradient boosting": "linear gradient boosting",
    "linear gradient boost": "linear gradient boosting",
    "linearboostregressor": "linear gradient boosting",
    "linearboostclassifier": "linear gradient boosting",

    "XGBoost": "XGBoost",
    "xgb": "XGBoost",
    "xgboost": "XGBoost",
    "extreme": "XGBoost",
    "extreme gradient boosting": "XGBoost",
    "xgbclassifier": "XGBoost",
    "xgbregressor": "XGBoost",

    "XGBoost forest": "XGBoost random forest",
    "xgb forest": "XGBoost random forest",
    "xgboost forest": "XGBoost random forest",
    "extreme forest": "XGBoost random forest",
    "extreme gradient boosting forest": "XGBoost random forest",
    "XGBoost random forest": "XGBoost random forest",
    "xgb random forest": "XGBoost random forest",
    "xgboost random forest": "XGBoost random forest",
    "extreme random forest": "XGBoost random forest",
    "extreme gradient boosting random forest": "XGBoost random forest",
    "xgbrandomforestregressor": "XGBoost random forest",
    "xgbrandomforestclassifier": "XGBoost random forest",

    "xgblinearclassifier": "XGBoost linear",
    "xgblinearregressor": "XGBoost linear",
    "xgblinear": "XGBoost linear",
    "xgb linear": "XGBoost linear",
    "linear xgb": "XGBoost linear",
    "linear xgboost": "XGBoost linear",
    "xgboost linear": "XGBoost linear",

    "LightGBM": "LightGBM",
    "lightgbm": "LightGBM",
    "lgbm": "LightGBM",
    "lgb": "LightGBM",
    "light": "LightGBM",
    "light gradient": "LightGBM",
    "lightweight gradient boosting": "LightGBM",
    "lgbmregressor": "LightGBM",
    "lgbmclassifier": "LightGBM",

    "lgbmlinearclassifier": "LightGBM linear",
    "lgbmlinearregressor": "LightGBM linear",
    "lgbmlinear": "LightGBM linear",
    "lgbm linear": "LightGBM linear",
    "linear lgbm": "LightGBM linear",
    "linear lightgbm": "LightGBM linear",
    "lightgbm linear": "LightGBM linear",

    "CatBoost": "CatBoost",
    "catboost": "CatBoost",
    "cat": "CatBoost",
    "cat boost": "CatBoost",
    "catboosting": "CatBoost",
    "cat boosting": "CatBoost",
    "catboostregressor": "CatBoost",
    "catboostclassifier": "CatBoost"
}